helialux
