Metadata-Version: 2.1
Name: pyHelialux
Version: 0.1.1
Summary: A library to communicate with with Juwel's HeliaLux Controller
Home-page: https://github.com/moretea/pyHelialux
Author: Maarten Hoogendoorn
License: UNKNOWN
Platform: UNKNOWN
Classifier: Development Status :: 3 - Alpha
Classifier: Environment :: Other Environment
Classifier: Intended Audience :: Developers
Classifier: License :: OSI Approved :: Apache Software License
Classifier: Operating System :: OS Independent
Classifier: Programming Language :: Python
Classifier: Topic :: Home Automation
Classifier: Topic :: Software Development :: Libraries :: Python Modules
